sql_writer/__init__.py
sql_writer/cant_use_.py
sql_writer/fix_bug_.py
sql_writer/sandbox1_.py
sql_writer_helper-0.1.0.dist-info/METADATA
sql_writer_helper-0.1.0.dist-info/WHEEL
sql_writer_helper-0.1.0.dist-info/top_level.txt
sql_writer_helper-0.1.0.dist-info/RECORD
